pinginstaller/Install_Update.py
pinginstaller/__init__.py
pinginstaller/__main__.py
pinginstaller/check_available_updates.py
pinginstaller/download_yml.py
pinginstaller/utils.py
pinginstaller/version.py
pinginstaller-2.1.6.dist-info/licenses/LICENSE
pinginstaller-2.1.6.dist-info/METADATA
pinginstaller-2.1.6.dist-info/WHEEL
pinginstaller-2.1.6.dist-info/top_level.txt
pinginstaller-2.1.6.dist-info/RECORD
