Metadata-Version: 2.4
Name: pinginstaller
Version: 2.1.6
Summary: Light-weight interface for running PING ecosystem (PINGMapper, etc.)
Author: Cameron Bodine
Author-email: bodine.cs@gmail.email
Project-URL: Issues, https://github.com/CameronBodine/PINGInstaller/issues
Project-URL: GitHub, https://github.com/CameronBodine/PINGInstaller
Project-URL: Homepage, https://cameronbodine.github.io/PINGMapper/
Keywords: pingmapper,sonar,ecology,remotesensing,sidescan,sidescan-sonar,aquatic,humminbird,lowrance,gis,oceanography,limnology
Classifier: Development Status :: 4 - Beta
Classifier: Programming Language :: Python :: 3
Classifier: License :: OSI Approved :: MIT License
Classifier: Operating System :: OS Independent
Classifier: Topic :: Scientific/Engineering
Classifier: Topic :: Scientific/Engineering :: Visualization
Classifier: Topic :: Scientific/Engineering :: Oceanography
Classifier: Topic :: Scientific/Engineering :: GIS
Classifier: Topic :: Scientific/Engineering :: Hydrology
Requires-Python: >3
License-File: LICENSE
Dynamic: author
Dynamic: author-email
Dynamic: classifier
Dynamic: description
Dynamic: description-content-type
Dynamic: keywords
Dynamic: license-file
Dynamic: project-url
Dynamic: requires-python
Dynamic: summary
